{
  "sentences": [
    {
      "sentence": "アルゴリズムとデータ構造の定義を理解する",
      "kana": "アルゴリズムとでーたこうぞうのていぎをりかいする",
      "drops": [],
      "audio": ""
    },
    {
      "sentence": "ちょっと恐いけど、ある意味爽快だよね",
      "kana": "ちょっとこわいけど、あるいみそうかいだよね",
      "drops": [],
      "audio": ""
    },
    {
      "sentence": "うちの家族は、これで潔白ですね",
      "kana": "うちのかぞくは、これでけっぱくですね",
      "drops": [],
      "audio": ""
    },
    {
      "sentence": "警察は事件が起きてから初めて動くしヒーローは遅れてやってくるのが定石です",
      "kana": "けいさつはじけんがおきるからはじうごくしヒーローはおくれるやってくるのがじょうせきです",
      "drops": [],
      "audio": ""
    }
  ]
}
